{
  "companyId": "16395f68-5373-4a81-bf1e-6c61f6cacdd7",
  "authTokenExpireIds": [],
  "connectorIds": [
    "pingOneSSOConnector",
    "errorConnector",
    "variablesConnector",
    "httpConnector",
    "pingOneMfaConnector",
    "annotationConnector"
  ],
  "createdDate": 1698064943072,
  "currentVersion": 52,
  "customerId": "f3e47d945ae971a4b4142ec75012d155",
  "description": "Cloned on Mon Oct 23 2023 11:39:40 GMT+0000 (Coordinated Universal Time). \nBX to Ping UX",
  "flowStatus": "enabled",
  "isOutputSchemaSaved": false,
  "name": "BXI-Registration (Ping UX)",
  "publishedVersion": 52,
  "settings": {
    "csp": "worker-src 'self' blob:; script-src 'self' https://cdn.jsdelivr.net https://code.jquery.com https://devsdk.singularkey.com http://cdnjs.cloudflare.com 'unsafe-inline' 'unsafe-eval';",
    "intermediateLoadingScreenCSS": "",
    "intermediateLoadingScreenHTML": "",
    "cssLinks": [
      "https://assets.pingone.com/ux/end-user-nano/0.1.0-alpha.1/end-user-nano.css",
      "https://assets.pingone.com/ux/astro-nano/0.1.0-alpha.7/icons.css"
    ],
    "useCustomCSS": true,
    "debugMode": true,
    "logLevel": 2,
    "css": ".companyLogo {\n    /* Ping Logo  */\n    content: url(\"https://assets.pingone.com/ux/ui-library/5.0.2/images/logo-pingidentity.png\");\n    height: 65px;\n    width: 65px;\n}\n\n/* OVERRIDES */\ndiv.bg-light.d-flex.flex-column.justify-content-center.align-items-center.position-absolute.top-0.start-0.bottom-0.end-0 {\n  background-image: unset !important;\n  background-size: unset !important;\n  background-repeat: unset !important;\n  --bs-bg-opacity: 0 !important;\n  background-color: unset !important;\n  right: unset !important;\n  left: unset !important;\n  top: unset !important;\n  bottom: unset !important;\n}",
    "customTitle": "BXI Registration",
    "customFaviconLink": "https://d3uinntk0mqu3p.cloudfront.net/branding/market/a3d073bc-3108-49ad-b96c-404bea59a1d0.png"
  },
  "timeouts": "null",
  "updatedDate": 1698064956859,
  "flowId": "928ddf98bc59efb5c1c5643a217ce437",
  "versionId": 52,
  "graphData": {
    "elements": {
      "nodes": [
        {
          "data": {
            "id": "l68q24zfrg",
            "nodeType": "EVAL",
            "properties": {
              "1h8u86n5qw": {
                "value": "anyTriggersFalse"
              },
              "z2mcqw4azg": {
                "value": "anyTriggersFalse"
              }
            }
          },
          "position": {
            "x": 1650,
            "y": 480
          },
          "group": "nodes",
          "removed": false,
          "selected": false,
          "selectable": true,
          "locked": false,
          "grabbable": true,
          "pannable": false,
          "classes": ""
        },
        {
          "data": {
            "id": "hwm8kns5vd",
            "nodeType": "CONNECTION",
            "connectionId": "94141bf2f1b9b59a5f5365ff135e02bb",
            "connectorId": "pingOneSSOConnector",
            "name": "PingOne",
            "label": "PingOne - Template",
            "status": "configured",
            "capabilityName": "createUser",
            "type": "action",
            "properties": {
              "username": {
                "value": "[\n  {\n    \"children\": [\n      {\n        \"text\": \"\"\n      },\n      {\n        \"text\": \"\"\n      },\n      {\n        \"type\": \"link\",\n        \"src\": \"http.svg\",\n        \"url\": \"email\",\n        \"data\": \"{{local.oyrj36mdip.payload.output.email}}\",\n        \"tooltip\": \"{{local.oyrj36mdip.payload.output.email}}\",\n        \"children\": [\n          {\n            \"text\": \"email\"\n          }\n        ]\n      },\n      {\n        \"text\": \"\"\n      }\n    ]\n  }\n]"
              },
              "populationId": {
                "value": "[\n  {\n    \"children\": [\n      {\n        \"text\": \"\"\n      },\n      {\n        \"text\": \"\"\n      },\n      {\n        \"type\": \"link\",\n        \"src\": \"variable.svg\",\n        \"url\": \"populationId\",\n        \"data\": \"{{global.variables.populationId}}\",\n        \"tooltip\": \"{{global.variables.populationId}}\",\n        \"children\": [\n          {\n            \"text\": \"populationId\"\n          }\n        ]\n      },\n      {\n        \"text\": \"\"\n      }\n    ]\n  }\n]"
              },
              "email": {
                "value": "[\n  {\n    \"children\": [\n      {\n        \"text\": \"\"\n      },\n      {\n        \"text\": \"\"\n      },\n      {\n        \"type\": \"link\",\n        \"src\": \"http.svg\",\n        \"url\": \"email\",\n        \"data\": \"{{local.oyrj36mdip.payload.output.email}}\",\n        \"tooltip\": \"{{local.oyrj36mdip.payload.output.email}}\",\n        \"children\": [\n          {\n            \"text\": \"email\"\n          }\n        ]\n      },\n      {\n        \"text\": \"\"\n      }\n    ]\n  }\n]"
              },
              "lifecycleStatus": {
                "value": "VERIFICATION_REQUIRED"
              },
              "nodeTitle": {
                "value": "Create PingOne User"
              },
              "password": {
                "value": "[\n  {\n    \"children\": [\n      {\n        \"text\": \"\"\n      },\n      {\n        \"text\": \"\"\n      },\n      {\n        \"type\": \"link\",\n        \"src\": \"http.svg\",\n        \"url\": \"password\",\n        \"data\": \"{{local.fuil2gnc5f.payload.output.password}}\",\n        \"tooltip\": \"{{local.fuil2gnc5f.payload.output.password}}\",\n        \"children\": [\n          {\n            \"text\": \"password\"\n          }\n        ]\n      },\n      {\n        \"text\": \"\"\n      }\n    ]\n  }\n]"
              },
              "passwordForCreateUser": {
                "value": "[\n  {\n    \"children\": [\n      {\n        \"text\": \"\"\n      },\n      {\n        \"text\": \"\"\n      },\n      {\n        \"type\": \"link\",\n        \"src\": \"http.svg\",\n        \"url\": \"password\",\n        \"data\": \"{{local.oyrj36mdip.payload.output.password}}\",\n        \"tooltip\": \"{{local.oyrj36mdip.payload.output.password}}\",\n        \"children\": [\n          {\n            \"text\": \"password\"\n          }\n        ]\n      },\n      {\n        \"text\": \"\"\n      }\n    ]\n  }\n]"
              },
              "given": {
                "value": "[\n  {\n    \"children\": [\n      {\n        \"text\": \"\"\n      },\n      {\n        \"text\": \"\"\n      },\n      {\n        \"type\": \"link\",\n        \"src\": \"http.svg\",\n        \"url\": \"firstName\",\n        \"data\": \"{{local.oyrj36mdip.payload.output.firstName}}\",\n        \"tooltip\": \"{{local.oyrj36mdip.payload.output.firstName}}\",\n        \"children\": [\n          {\n            \"text\": \"firstName\"\n          }\n        ]\n      },\n      {\n        \"text\": \"\"\n      }\n    ]\n  }\n]"
              },
              "family": {
                "value": "[\n  {\n    \"children\": [\n      {\n        \"text\": \"\"\n      },\n      {\n        \"text\": \"\"\n      },\n      {\n        \"type\": \"link\",\n        \"src\": \"http.svg\",\n        \"url\": \"lastName\",\n        \"data\": \"{{local.oyrj36mdip.payload.output.lastName}}\",\n        \"tooltip\": \"{{local.oyrj36mdip.payload.output.lastName}}\",\n        \"children\": [\n          {\n            \"text\": \"lastName\"\n          }\n        ]\n      },\n      {\n        \"text\": \"\"\n      }\n    ]\n  }\n]"
              },
              "additionalUserProperties": {
                "value": []
              }
            }
          },
          "position": {
            "x": 930,
            "y": 480
          },
          "group": "nodes",
          "removed": false,
          "selected": false,
          "selectable": true,
          "locked": false,
          "grabbable": true,
          "pannable": false,
          "classes": ""
        },
        {
          "data": {
            "id": "591k4nizoj",
            "nodeType": "EVAL",
            "properties": {
              "70xyz374za": {
                "value": "anyTriggersFalse"
              }
            }
          },
          "position": {
            "x": 1050,
            "y": 480
          },
          "group": "nodes",
          "removed": false,
          "selected": false,
          "selectable": true,
          "locked": false,
          "grabbable": true,
          "pannable": false,
          "classes": ""
        },
        {
          "data": {
            "id": "rcbpcr6g10",
            "nodeType": "CONNECTION",
            "connectionId": "94141bf2f1b9b59a5f5365ff135e02bb",
            "connectorId": "pingOneSSOConnector",
            "name": "PingOne",
            "label": "PingOne - Template",
            "status": "configured",
            "capabilityName": "verifyEmail",
            "type": "action",
            "properties": {
              "identifier": {
                "value": "[\n  {\n    \"children\": [\n      {\n        \"text\": \"\"\n      },\n      {\n        \"text\": \"\"\n      },\n      {\n        \"type\": \"link\",\n        \"src\": \"pingIdentity.svg\",\n        \"url\": \"id\",\n        \"data\": \"{{local.hwm8kns5vd.payload.output.rawResponse.id}}\",\n        \"tooltip\": \"{{local.hwm8kns5vd.payload.output.rawResponse.id}}\",\n        \"children\": [\n          {\n            \"text\": \"id\"\n          }\n        ]\n      },\n      {\n        \"text\": \"\"\n      }\n    ]\n  }\n]"
              },
              "verificationCode": {
                "value": "[\n  {\n    \"children\": [\n      {\n        \"text\": \"\"\n      },\n      {\n        \"text\": \"\"\n      },\n      {\n        \"type\": \"link\",\n        \"src\": \"http.svg\",\n        \"url\": \"verifyCode\",\n        \"data\": \"{{local.bubzo4dlxp.payload.output.verifyCode}}\",\n        \"tooltip\": \"{{local.bubzo4dlxp.payload.output.verifyCode}}\",\n        \"children\": [\n          {\n            \"text\": \"verifyCode\"\n          }\n        ]\n      },\n      {\n        \"text\": \"\"\n      }\n    ]\n  }\n]"
              },
              "nodeTitle": {
                "value": "Validate Verification Code"
              }
            }
          },
          "position": {
            "x": 1530,
            "y": 480
          },
          "group": "nodes",
          "removed": false,
          "selected": false,
          "selectable": true,
          "locked": false,
          "grabbable": true,
          "pannable": false,
          "classes": ""
        },
        {
          "data": {
            "id": "z2mcqw4azg",
            "nodeType": "CONNECTION",
            "connectionId": "6d8f6f706c45fd459a86b3f092602544",
            "connectorId": "errorConnector",
            "name": "Error Customize",
            "label": "errorConnector",
            "status": "configured",
            "capabilityName": "customErrorMessage",
            "type": "action",
            "properties": {
              "nodeTitle": {
                "value": "Invalid Code"
              },
              "errorMessage": {
                "value": "[\n  {\n    \"children\": [\n      {\n        \"text\": \"The provided verification code is invalid\"\n      }\n    ]\n  }\n]"
              },
              "backgroundColor": {
                "value": "#ffc8c1ff"
              }
            }
          },
          "position": {
            "x": 1830,
            "y": 690
          },
          "group": "nodes",
          "removed": false,
          "selected": false,
          "selectable": true,
          "locked": false,
          "grabbable": true,
          "pannable": false,
          "classes": ""
        },
        {
          "data": {
            "id": "70xyz374za",
            "nodeType": "CONNECTION",
            "connectionId": "6d8f6f706c45fd459a86b3f092602544",
            "connectorId": "errorConnector",
            "name": "Error Customize",
            "label": "errorConnector",
            "status": "configured",
            "capabilityName": "customErrorMessage",
            "type": "action",
            "properties": {
              "nodeTitle": {
                "value": "User Create Error"
              },
              "errorMessage": {
                "value": "[\n  {\n    \"children\": [\n      {\n        \"text\": \"Username is already registered\"\n      }\n    ]\n  }\n]"
              },
              "backgroundColor": {
                "value": "#ffc8c1ff"
              }
            }
          },
          "position": {
            "x": 1230,
            "y": 690
          },
          "group": "nodes",
          "removed": false,
          "selected": false,
          "selectable": true,
          "locked": false,
          "grabbable": true,
          "pannable": false,
          "classes": ""
        },
        {
          "data": {
            "id": "q3tujxeb1w",
            "nodeType": "EVAL"
          },
          "position": {
            "x": 750,
            "y": 480
          },
          "group": "nodes",
          "removed": false,
          "selected": false,
          "selectable": true,
          "locked": false,
          "grabbable": true,
          "pannable": false,
          "classes": ""
        },
        {
          "data": {
            "id": "b03wrisvgh",
            "nodeType": "EVAL"
          },
          "position": {
            "x": 1350,
            "y": 480
          },
          "group": "nodes",
          "removed": false,
          "selected": false,
          "selectable": true,
          "locked": false,
          "grabbable": true,
          "pannable": false,
          "classes": ""
        },
        {
          "data": {
            "id": "3p9s1p9kfx",
            "nodeType": "CONNECTION",
            "connectionId": "06922a684039827499bdbdd97f49827b",
            "connectorId": "variablesConnector",
            "name": "Variables",
            "label": "WesVariables",
            "status": "configured",
            "capabilityName": "saveValue",
            "type": "trigger",
            "properties": {
              "nodeTitle": {
                "value": "Set Population ID"
              },
              "saveVariables": {
                "value": [
                  {
                    "name": "populationId",
                    "value": "[\n  {\n    \"children\": [\n      {\n        \"text\": \"bf889865-c159-4944-b515-4bbf5149c85a\"\n      }\n    ]\n  }\n]",
                    "key": 0.7679110133136258,
                    "label": "populationId (string - flowInstance)",
                    "type": "string"
                  }
                ]
              }
            }
          },
          "position": {
            "x": 330,
            "y": 480
          },
          "group": "nodes",
          "removed": false,
          "selected": false,
          "selectable": true,
          "locked": false,
          "grabbable": true,
          "pannable": false,
          "classes": ""
        },
        {
          "data": {
            "id": "bzmvingg2c",
            "nodeType": "EVAL",
            "properties": {
              "oyrj36mdip": {
                "value": "allTriggersTrue"
              },
              "6ounnfojy0": {
                "value": "anyTriggersFalse"
              }
            }
          },
          "position": {
            "x": 450,
            "y": 480
          },
          "group": "nodes",
          "removed": false,
          "selected": false,
          "selectable": true,
          "locked": false,
          "grabbable": true,
          "pannable": false,
          "classes": ""
        },
        {
          "data": {
            "id": "bubzo4dlxp",
            "nodeType": "CONNECTION",
            "connectionId": "867ed4363b2bc21c860085ad2baa817d",
            "connectorId": "httpConnector",
            "name": "Http",
            "label": "Http",
            "status": "configured",
            "capabilityName": "customHTMLTemplate",
            "type": "trigger",
            "properties": {
              "messageTitle": {
                "value": "[\n  {\n    \"children\": [\n      {\n        \"text\": \"Success\"\n      }\n    ]\n  }\n]"
              },
              "customHTML": {
                "value": "<div\n  class=\"bg-light d-flex flex-column justify-content-center align-items-center position-absolute top-0 start-0 bottom-0 end-0 overflow-auto\">\n<div style=\"max-width: 400px; min-width: 400px; width: 100%\">\n    <div class=\"card shadow mb-5\">\n      <div class=\"card-body p-5 d-flex flex-column\">\n        <img class=\"companyLogo align-self-center mb-5\" alt=\"Ping Identity\" />\n        \n        {{#if title}}\n        <h1 class=\"text-center mb-4\">{{title}}</h1>\n        {{/if}}\n\n        {{#if iconClass}}\n        <p class=\"text-center\"><i class=\"mdi {{iconClass}} text-dark display-6\" aria-hidden=\"true\"></i> \n        {{/if}}\n        \n        {{#if textOne}}\n        <p class=\"text-muted text-center\">{{textOne}}</p>\n        {{/if}}\n\n        {{#if textTwo}}\n        <p class=\"text-muted text-center\">{{textTwo}}</p>\n        {{/if}}\n\n        <p class=\"text-danger mdi mdi-alert-circle\" data-id=\"feedback\" data-skcomponent=\"skerror\"></p>\n        <form id=\"otpForm\" data-id=\"otpForm\">\n          <div class=\"mb-4 form-floating\">\n            <input class=\"form-control\" type=\"text\" name=\"verifyCode\" placeholder=\"Verification Code\" autocomplete=\"off\"\n              data-id=\"verifyCode\" id=\"verifyCode\" maxlength=\"{{codeMaxLength}}\"/>\n            <label class=\"form-label\" for=\"verifyCode\" >Verification Code</label>\n            <div data-skcomponent=\"skerrormessage\" class=\"text-danger mt-2\" data-skerrorid=\"verifyCode\"></div> \n          </div>\n          <div class=\"d-flex flex-column\">\n            <button class=\"btn btn-primary flex-grow-1\" data-skcomponent=\"skbutton\" data-skbuttontype=\"form-submit\"\n              data-skrequiredinputs=\"verifyCode\" data-skform=\"otpForm\" id=\"btnVerify\" data-skbuttonvalue=\"VERIFY\">Verify</button>\n          </div>\n        </form>\n      </div>\n    </div>\n  </div>\n</div>"
              },
              "formFieldsList": {
                "value": [
                  {
                    "propertyName": "verifyCode",
                    "preferredControlType": "textField",
                    "preferredDataType": "string",
                    "value": "",
                    "hashedVisibility": false
                  },
                  {
                    "preferredControlType": "textField",
                    "preferredDataType": "string",
                    "propertyName": "buttonValue"
                  }
                ]
              },
              "nodeTitle": {
                "value": "Passcode Verification (OTP)"
              },
              "customScript": {
                "value": "const setFieldFocus = (id) => {\n    const element = document.getElementById(id);\n    if (element) {\n        element.focus();\n    }\n}\n\nconst start = () => {\n    setFieldFocus(\"verifyCode\")\n}\n\nif (document.readyState === \"loading\") {\n    // Loading hasn't finished yet\n    document.addEventListener(\"DOMContentLoaded\", start);\n} else {\n    // `DOMContentLoaded` has already fired\n    start();\n}"
              },
              "nodeDescription": {
                "value": "One-time Passcode entry"
              },
              "customCSS": {
                "value": "#verifyCode {\n    text-align: center;\n    font-size: x-large;\n    letter-spacing: 6px;\n}\n\nlabel.form-label {\n    padding: 22px 10px;\n}"
              },
              "inputSchema": {
                "value": "{\n    \"type\": \"object\",\n    \"properties\": {\n        \"title\": {\n            \"type\": \"string\",\n            \"displayName\": \"Title\",\n            \"preferredControlType\": \"textField\",\n            \"enableParameters\": true,\n            \"propertyName\": \"title\"\n        },\n        \"textOne\": {\n            \"type\": \"string\",\n            \"displayName\": \"Text One\",\n            \"preferredControlType\": \"textField\",\n            \"enableParameters\": true,\n            \"propertyName\": \"textOne\"\n        },\n        \"textTwo\": {\n            \"type\": \"string\",\n            \"displayName\": \"Text Two\",\n            \"preferredControlType\": \"textField\",\n            \"enableParameters\": true,\n            \"propertyName\": \"textTwo\"\n        },\n        \"iconClass\": {\n            \"type\": \"string\",\n            \"displayName\": \"Icon Class\",\n            \"preferredControlType\": \"textField\",\n            \"enableParameters\": true,\n            \"propertyName\": \"iconClass\"\n        },\n        \"codeMaxLength\": {\n            \"type\": \"string\",\n            \"displayName\": \"Code Max Length\",\n            \"preferredControlType\": \"textField\",\n            \"enableParameters\": true,\n            \"propertyName\": \"codeMaxLength\"\n        }\n    }\n}"
              },
              "title": {
                "value": "[\n  {\n    \"children\": [\n      {\n        \"text\": \"Email Verification\"\n      }\n    ]\n  }\n]"
              },
              "textOne": {
                "value": "[\n  {\n    \"children\": [\n      {\n        \"text\": \" We’ve sent a verification email to your email address.\"\n      }\n    ]\n  }\n]"
              },
              "iconClass": {
                "value": "[\n  {\n    \"children\": [\n      {\n        \"text\": \"mdi-comment-text-outline\"\n      }\n    ]\n  }\n]"
              },
              "codeMaxLength": {
                "value": "[\n  {\n    \"children\": [\n      {\n        \"text\": \"8\"\n      }\n    ]\n  }\n]"
              },
              "textTwo": {
                "value": "[\n  {\n    \"children\": [\n      {\n        \"text\": \"Please verify your email to finish setting up your account.\"\n      }\n    ]\n  }\n]"
              },
              "validationRules": {
                "value": [
                  {
                    "propertyName": "verifyCode",
                    "rules": [
                      {
                        "ruleName": "presence",
                        "message": "Input OTP code you received."
                      }
                    ]
                  }
                ]
              }
            },
            "idUnique": "4zzc0e5nj0"
          },
          "position": {
            "x": 1230,
            "y": 480
          },
          "group": "nodes",
          "removed": false,
          "selected": false,
          "selectable": true,
          "locked": false,
          "grabbable": true,
          "pannable": false,
          "classes": ""
        },
        {
          "data": {
            "id": "omghnpt8gt",
            "nodeType": "CONNECTION",
            "connectionId": "b72bd44e6be8180bd5988ac74cd9c949",
            "connectorId": "pingOneMfaConnector",
            "name": "PingOne MFA",
            "label": "Ping One Mfa [2022-05-03]",
            "status": "configured",
            "capabilityName": "updateUserMFAEnabled",
            "type": "action",
            "properties": {
              "userId": {
                "value": "[\n  {\n    \"children\": [\n      {\n        \"text\": \"\"\n      },\n      {\n        \"text\": \"\"\n      },\n      {\n        \"type\": \"link\",\n        \"src\": \"pingIdentity.svg\",\n        \"url\": \"id\",\n        \"data\": \"{{local.hwm8kns5vd.payload.output.user.id}}\",\n        \"tooltip\": \"{{local.hwm8kns5vd.payload.output.user.id}}\",\n        \"children\": [\n          {\n            \"text\": \"id\"\n          }\n        ]\n      },\n      {\n        \"text\": \"\"\n      }\n    ]\n  }\n]"
              },
              "nodeTitle": {
                "value": "Update MFA Status"
              }
            }
          },
          "position": {
            "x": 1830,
            "y": 480
          },
          "group": "nodes",
          "removed": false,
          "selected": false,
          "selectable": true,
          "locked": false,
          "grabbable": true,
          "pannable": false,
          "classes": ""
        },
        {
          "data": {
            "id": "64lc0zonuu",
            "nodeType": "EVAL",
            "properties": {
              "kotjm31vdk": {
                "value": "anyTriggersFalse"
              }
            }
          },
          "position": {
            "x": 1950,
            "y": 480
          },
          "group": "nodes",
          "removed": false,
          "selected": false,
          "selectable": true,
          "locked": false,
          "grabbable": true,
          "pannable": false,
          "classes": ""
        },
        {
          "data": {
            "id": "9g1rb2rxt5",
            "nodeType": "EVAL",
            "properties": {
              "kotjm31vdk": {
                "value": "anyTriggersFalse"
              }
            }
          },
          "position": {
            "x": 2250,
            "y": 480
          },
          "group": "nodes",
          "removed": false,
          "selected": false,
          "selectable": true,
          "locked": false,
          "grabbable": true,
          "pannable": false,
          "classes": ""
        },
        {
          "data": {
            "id": "kotjm31vdk",
            "nodeType": "CONNECTION",
            "connectionId": "6d8f6f706c45fd459a86b3f092602544",
            "connectorId": "errorConnector",
            "name": "Error Customize",
            "label": "Error Customize",
            "status": "configured",
            "capabilityName": "customErrorMessage",
            "type": "action",
            "properties": {
              "backgroundColor": {
                "value": "#ffc8c1ff"
              },
              "nodeTitle": {
                "value": "MFA Enrollment Error"
              },
              "errorMessage": {
                "value": "[\n  {\n    \"children\": [\n      {\n        \"text\": \"Error enrolling MFA device\"\n      }\n    ]\n  }\n]"
              }
            }
          },
          "position": {
            "x": 2430,
            "y": 690
          },
          "group": "nodes",
          "removed": false,
          "selected": false,
          "selectable": true,
          "locked": false,
          "grabbable": true,
          "pannable": false,
          "classes": ""
        },
        {
          "data": {
            "id": "rogr26k0ca",
            "nodeType": "CONNECTION",
            "connectionId": "b72bd44e6be8180bd5988ac74cd9c949",
            "connectorId": "pingOneMfaConnector",
            "name": "PingOne MFA",
            "label": "PingOne MFA",
            "status": "configured",
            "capabilityName": "createDevice",
            "type": "action",
            "properties": {
              "userId": {
                "value": "[\n  {\n    \"children\": [\n      {\n        \"text\": \"\"\n      },\n      {\n        \"text\": \"\"\n      },\n      {\n        \"text\": \"\"\n      },\n      {\n        \"type\": \"link\",\n        \"src\": \"pingIdentity.svg\",\n        \"url\": \"id\",\n        \"data\": \"{{local.hwm8kns5vd.payload.output.user.id}}\",\n        \"tooltip\": \"{{local.hwm8kns5vd.payload.output.user.id}}\",\n        \"children\": [\n          {\n            \"text\": \"id\"\n          }\n        ]\n      },\n      {\n        \"text\": \"\"\n      }\n    ]\n  }\n]"
              },
              "deviceType": {
                "value": "EMAIL"
              },
              "status": {
                "value": "ACTIVE"
              },
              "email": {
                "value": "[\n  {\n    \"children\": [\n      {\n        \"text\": \"\"\n      },\n      {\n        \"text\": \"\"\n      },\n      {\n        \"type\": \"link\",\n        \"src\": \"pingIdentity.svg\",\n        \"url\": \"email\",\n        \"data\": \"{{local.hwm8kns5vd.payload.output.user.email}}\",\n        \"tooltip\": \"{{local.hwm8kns5vd.payload.output.user.email}}\",\n        \"children\": [\n          {\n            \"text\": \"email\"\n          }\n        ]\n      },\n      {\n        \"text\": \"\"\n      }\n    ]\n  }\n]"
              },
              "customDeviceType": {
                "value": "{}"
              },
              "customNotificationPolicyId": {
                "value": "{}"
              },
              "customTemplateVariant": {
                "value": "{}"
              }
            }
          },
          "position": {
            "x": 2130,
            "y": 480
          },
          "group": "nodes",
          "removed": false,
          "selected": false,
          "selectable": true,
          "locked": false,
          "grabbable": true,
          "pannable": false,
          "classes": ""
        },
        {
          "data": {
            "id": "poluqyu08d",
            "nodeType": "ANNOTATION",
            "name": "Annotation",
            "connectionId": "921bfae85c38ed45045e07be703d86b8",
            "connectorId": "annotationConnector",
            "capabilityName": "updateAnnotationProperties",
            "type": "action",
            "properties": {
              "backgroundColor": {
                "value": "#4462edff"
              },
              "annotationTextColor": {
                "value": "#ffffffff"
              },
              "annotation": {
                "value": "BXI Registration (Ping UX)"
              },
              "width": {
                "value": 2350
              },
              "fontStyle": {
                "value": "bold"
              },
              "fontSize": {
                "value": 16
              },
              "fontFamily": {
                "value": "sans-serif"
              },
              "cornerRadius": {
                "value": 8
              }
            },
            "status": "configured"
          },
          "position": {
            "x": 214,
            "y": 214
          },
          "group": "nodes",
          "removed": false,
          "selected": false,
          "selectable": true,
          "locked": false,
          "grabbable": true,
          "pannable": false,
          "classes": ""
        },
        {
          "data": {
            "id": "oyrj36mdip",
            "nodeType": "CONNECTION",
            "connectionId": "867ed4363b2bc21c860085ad2baa817d",
            "connectorId": "httpConnector",
            "name": "Http",
            "label": "Http (Use this for form + custom messages)",
            "status": "configured",
            "capabilityName": "customHTMLTemplate",
            "type": "trigger",
            "properties": {
              "nodeTitle": {
                "value": "Registration form"
              },
              "formFieldsList": {
                "value": [
                  {
                    "propertyName": "firstName",
                    "preferredControlType": "textField",
                    "preferredDataType": "string",
                    "value": "",
                    "hashedVisibility": false,
                    "displayName": "First Name"
                  },
                  {
                    "propertyName": "lastName",
                    "preferredControlType": "textField",
                    "preferredDataType": "string",
                    "value": "",
                    "hashedVisibility": false,
                    "displayName": "Last Name"
                  },
                  {
                    "propertyName": "email",
                    "preferredControlType": "textField",
                    "preferredDataType": "string",
                    "value": "",
                    "hashedVisibility": false,
                    "displayName": "Email"
                  },
                  {
                    "propertyName": "password",
                    "preferredControlType": "textField",
                    "preferredDataType": "string",
                    "value": "",
                    "hashedVisibility": true,
                    "displayName": "Password"
                  },
                  {
                    "preferredControlType": "textField",
                    "preferredDataType": "string",
                    "propertyName": "buttonValue"
                  }
                ]
              },
              "customHTML": {
                "value": "<div\n  class=\"bg-light d-flex flex-column justify-content-center align-items-center position-absolute top-0 start-0 bottom-0 end-0\">\n  <div style=\"max-width: 400px; width: 100%\">\n    <div class=\"card shadow mb-5\">\n      <div class=\"card-body p-5 d-flex flex-column\">\n        <img class=\"companyLogo align-self-center mb-5\" alt=\"{{global.variables.companyName}}\" />\n\n        {{#if title}}\n        <h1 class=\"text-center mb-4\">{{title}}</h1>\n        {{/if}}\n\n        {{#if textOne}}\n        <p class=\"text-muted text-center\">{{textOne}}</p>\n        {{/if}}\n\n        {{#if textTwo}}\n        <p class=\"text-muted text-center\">{{textTwo}}</p>\n        {{/if}}\n\n        <p id=\"feedback\" data-id=\"feedback\" class=\"text-danger mdi mdi-alert-circle\" data-skcomponent=\"skerror\"></p>\n        <form id=\"registrationForm\" data-id=\"registrationForm\" class=\"form\">\n          <div class=\"mb-4 form-floating\">\n            <input id=\"email\" data-id=\"email\" class=\"form-control\" type=\"text\" name=\"email\" placeholder=\"Email Address\"\n              autocomplete=\"off\" />\n            <label id=\"emailLabel\" data-id=\"emailLabel\" class=\"form-label\" for=\"email\">Email Address</label>\n             <div data-skcomponent=\"skerrormessage\" class=\"text-danger mt-1\" data-skerrorid=\"email\"></div>\n          </div>\n          <div class=\"mb-4 form-floating\">\n            <input id=\"firstName\" data-id=\"firstName\" class=\"form-control\" type=\"text\" name=\"firstName\"\n              placeholder=\"First Name\" autocomplete=\"off\" />\n            <label id=\"firstNameLabel\" data-id=\"firstNameLabel\" class=\"form-label\" for=\"firstName\">First Name</label>\n            <div data-skcomponent=\"skerrormessage\" class=\"text-danger mt-1\" data-skerrorid=\"firstName\"></div>\n          </div>\n          <div class=\"mb-4 form-floating\">\n            <input id=\"lastName\" data-id=\"lastName\" class=\"form-control\" type=\"text\" placeholder=\"Last Name\"\n              autocomplete=\"off\" name=\"lastName\" />\n            <label id=\"lastNameLabel\" data-id=\"lastNameLabel\" class=\"form-label\" for=\"lastName\">Last Name</label>\n            <div data-skcomponent=\"skerrormessage\" class=\"text-danger mt-1\" data-skerrorid=\"lastName\"></div>\n          </div>\n          <div id=\"passwordContainer\" class=\"mb-2 form-floating\">\n            <input id=\"password\" data-id=\"password\" class=\"form-control\" type=\"password\" placeholder=\"Password\"\n              autocomplete=\"off\" name=\"password\" />\n            <label id=\"passwordLabel\" data-id=\"passwordLabel\" class=\"form-label\" for=\"password\">Password</label>\n            \n          </div>\n          <div data-skcomponent=\"skerrormessage\" class=\"text-danger mt-1\" data-skerrorid=\"password\"></div>\n          <div class=\"d-flex flex-column\">\n            <button id=\"submitBtn\" data-id=\"submitBtn\" class=\"btn btn-primary mb-3 mt-3\" type=\"submit\"\n              data-skcomponent=\"skbutton\" data-skbuttontype=\"form-submit\" data-skform=\"registrationForm\"\n              data-skbuttonvalue=\"REGISTER\">\n              Continue\n            </button>\n          </div>\n        </form>\n      </div>\n    </div>\n  </div>\n</div>"
              },
              "customCSS": {},
              "customScript": {
                "value": "const setFieldFocus = (id) => {\r\n    const element = document.getElementById(id);\r\n    if (element) {\r\n        element.focus();\r\n    }\r\n}\r\n\r\nconst makePasswordToggle = (id) => {\r\n    let container = document.getElementById(id);\r\n\r\n    if (container) {\r\n        let password = container.getElementsByTagName(\"input\")[0];\r\n        let toggler = document.createElement(\"button\");\r\n        toggler.setAttribute(\"type\", \"button\");\r\n        toggler.setAttribute(\"aria-label\", \"Show/Hide Password\");\r\n        toggler.className = \"btn mdi mdi-eye-off-outline position-absolute end-0 top-50 translate-middle-y\";\r\n        container.appendChild(toggler);\r\n\r\n        function showHidePassword() {\r\n            if (password.type == \"password\") {\r\n                password.setAttribute(\"type\", \"text\");\r\n                toggler.classList.add(\"mdi-eye-outline\");\r\n                toggler.classList.remove(\"mdi-eye-off-outline\");\r\n            } else {\r\n                toggler.classList.add(\"mdi-eye-off-outline\");\r\n                toggler.classList.remove(\"mdi-eye-outline\");\r\n                password.setAttribute(\"type\", \"password\");\r\n            }\r\n            password.focus();\r\n        };\r\n\r\n        toggler.addEventListener(\"click\", showHidePassword);\r\n    }\r\n}\r\n\r\nconst start = () => {\r\n    makePasswordToggle(\"passwordContainer\");\r\n    setFieldFocus(\"email\")\r\n}\r\n\r\nif (document.readyState === \"loading\") {\r\n    // Loading hasn't finished yet\r\n    document.addEventListener(\"DOMContentLoaded\", start);\r\n} else {\r\n    // `DOMContentLoaded` has already fired\r\n    start();\r\n}"
              },
              "validationRules": {
                "value": [
                  {
                    "propertyName": "email",
                    "rules": [
                      {
                        "ruleName": "email",
                        "message": "Must be a valid email format."
                      },
                      {
                        "ruleName": "presence",
                        "message": "Email is a required field."
                      }
                    ]
                  },
                  {
                    "propertyName": "password",
                    "rules": [
                      {
                        "ruleName": "presence",
                        "message": "Password is a required field."
                      },
                      {
                        "ruleName": "format",
                        "pattern": "^(?=.*[a-z])(?=.*[A-Z])(?=.*\\d)(?=.*[@$!.,%*?&])[A-Za-z\\d@$!.,%*?&]{8,}$",
                        "message": "Must contain 8 or more characters that are of at least one number, and one uppercase, one lowercase letter, and one or more of the following special characters @$!.,%*?&."
                      }
                    ]
                  },
                  {
                    "propertyName": "firstName",
                    "rules": [
                      {
                        "ruleName": "presence",
                        "message": "First name is a required field."
                      }
                    ]
                  },
                  {
                    "propertyName": "lastName",
                    "rules": [
                      {
                        "ruleName": "presence",
                        "message": "Last name is a required field."
                      }
                    ]
                  }
                ]
              },
              "nodeDescription": {
                "value": "Displays the form to collect user info"
              },
              "inputSchema": {
                "value": "{\n    \"type\": \"object\",\n    \"properties\": {\n        \"title\": {\n            \"type\": \"string\",\n            \"displayName\": \"Title\",\n            \"preferredControlType\": \"textField\",\n            \"enableParameters\": true,\n            \"propertyName\": \"title\"\n        },\n        \"textOne\": {\n            \"type\": \"string\",\n            \"displayName\": \"Text One\",\n            \"preferredControlType\": \"textField\",\n            \"enableParameters\": true,\n            \"propertyName\": \"textOne\"\n        },\n        \"textTwo\": {\n            \"type\": \"string\",\n            \"displayName\": \"Text Two\",\n            \"preferredControlType\": \"textField\",\n            \"enableParameters\": true,\n            \"propertyName\": \"textTwo\"\n        }\n    }\n}"
              },
              "title": {
                "value": "[\n  {\n    \"children\": [\n      {\n        \"text\": \"Create Your Profile\"\n      }\n    ]\n  }\n]"
              },
              "textOne": {
                "value": "[\n  {\n    \"children\": [\n      {\n        \"text\": \"Please complete the form below to create your profile.\"\n      }\n    ]\n  }\n]"
              }
            },
            "idUnique": "e9zf5ebk6y"
          },
          "position": {
            "x": 630,
            "y": 480
          },
          "group": "nodes",
          "removed": false,
          "selected": false,
          "selectable": true,
          "locked": false,
          "grabbable": true,
          "pannable": false,
          "classes": ""
        },
        {
          "data": {
            "id": "hxs0c9l4q9",
            "nodeType": "ANNOTATION",
            "name": "Annotation",
            "connectionId": "921bfae85c38ed45045e07be703d86b8",
            "connectorId": "annotationConnector",
            "capabilityName": "updateAnnotationProperties",
            "type": "action",
            "properties": {
              "backgroundColor": {
                "value": "#f2f3f4ff"
              },
              "annotationTextColor": {
                "value": "#000000"
              },
              "annotation": {
                "value": "Standard Registration Form"
              },
              "width": {
                "value": 240
              },
              "fontSize": {
                "value": 14
              },
              "fontFamily": {
                "value": "sans-serif"
              },
              "cornerRadius": {
                "value": 8
              },
              "strokeEnabled": {
                "value": true
              },
              "strokeWidth": {
                "value": 1
              },
              "strokeColor": {
                "value": "#181818ff"
              }
            },
            "status": "configured"
          },
          "position": {
            "x": 510,
            "y": 360
          },
          "group": "nodes",
          "removed": false,
          "selected": false,
          "selectable": true,
          "locked": false,
          "grabbable": true,
          "pannable": false,
          "classes": ""
        },
        {
          "data": {
            "id": "anc8hqz6qr",
            "nodeType": "ANNOTATION",
            "name": "Annotation",
            "connectionId": "921bfae85c38ed45045e07be703d86b8",
            "connectorId": "annotationConnector",
            "capabilityName": "updateAnnotationProperties",
            "type": "action",
            "properties": {
              "backgroundColor": {
                "value": "#f2f3f4ff"
              },
              "annotationTextColor": {
                "value": "#000000"
              },
              "annotation": {
                "value": "Create New User in PingOne"
              },
              "width": {
                "value": 240
              },
              "fontSize": {
                "value": 14
              },
              "fontFamily": {
                "value": "sans-serif"
              },
              "cornerRadius": {
                "value": 8
              },
              "strokeEnabled": {
                "value": true
              },
              "strokeWidth": {
                "value": 1
              },
              "strokeColor": {
                "value": "#181818ff"
              }
            },
            "status": "configured"
          },
          "position": {
            "x": 810,
            "y": 360
          },
          "group": "nodes",
          "removed": false,
          "selected": false,
          "selectable": true,
          "locked": false,
          "grabbable": true,
          "pannable": false,
          "classes": ""
        },
        {
          "data": {
            "id": "za2db70qe7",
            "nodeType": "ANNOTATION",
            "name": "Annotation",
            "connectionId": "921bfae85c38ed45045e07be703d86b8",
            "connectorId": "annotationConnector",
            "capabilityName": "updateAnnotationProperties",
            "type": "action",
            "properties": {
              "backgroundColor": {
                "value": "#f2f3f4ff"
              },
              "annotationTextColor": {
                "value": "#000000"
              },
              "annotation": {
                "value": "User Create Error"
              },
              "width": {
                "value": 240
              },
              "fontSize": {
                "value": 14
              },
              "fontFamily": {
                "value": "sans-serif"
              },
              "cornerRadius": {
                "value": 8
              },
              "strokeEnabled": {
                "value": true
              },
              "strokeWidth": {
                "value": 1
              },
              "strokeColor": {
                "value": "#181818ff"
              }
            },
            "status": "configured",
            "idUnique": "a7e7il3z1n"
          },
          "position": {
            "x": 1110,
            "y": 600
          },
          "group": "nodes",
          "removed": false,
          "selected": false,
          "selectable": true,
          "locked": false,
          "grabbable": true,
          "pannable": false,
          "classes": ""
        },
        {
          "data": {
            "id": "f64ye4ndo1",
            "nodeType": "ANNOTATION",
            "name": "Annotation",
            "connectionId": "921bfae85c38ed45045e07be703d86b8",
            "connectorId": "annotationConnector",
            "capabilityName": "updateAnnotationProperties",
            "type": "action",
            "properties": {
              "backgroundColor": {
                "value": "#f2f3f4ff"
              },
              "annotationTextColor": {
                "value": "#000000"
              },
              "annotation": {
                "value": "Enter Verification Code"
              },
              "width": {
                "value": 240
              },
              "fontSize": {
                "value": 14
              },
              "fontFamily": {
                "value": "sans-serif"
              },
              "cornerRadius": {
                "value": 8
              },
              "strokeEnabled": {
                "value": true
              },
              "strokeWidth": {
                "value": 1
              },
              "strokeColor": {
                "value": "#181818ff"
              }
            },
            "status": "configured"
          },
          "position": {
            "x": 1110,
            "y": 360
          },
          "group": "nodes",
          "removed": false,
          "selected": false,
          "selectable": true,
          "locked": false,
          "grabbable": true,
          "pannable": false,
          "classes": ""
        },
        {
          "data": {
            "id": "1iyzj5kwnh",
            "nodeType": "ANNOTATION",
            "name": "Annotation",
            "connectionId": "921bfae85c38ed45045e07be703d86b8",
            "connectorId": "annotationConnector",
            "capabilityName": "updateAnnotationProperties",
            "type": "action",
            "properties": {
              "backgroundColor": {
                "value": "#f2f3f4ff"
              },
              "annotationTextColor": {
                "value": "#000000"
              },
              "annotation": {
                "value": "Validate Verification Code"
              },
              "width": {
                "value": 240
              },
              "fontSize": {
                "value": 14
              },
              "fontFamily": {
                "value": "sans-serif"
              },
              "cornerRadius": {
                "value": 8
              },
              "strokeEnabled": {
                "value": true
              },
              "strokeWidth": {
                "value": 1
              },
              "strokeColor": {
                "value": "#181818ff"
              }
            },
            "status": "configured"
          },
          "position": {
            "x": 1410,
            "y": 360
          },
          "group": "nodes",
          "removed": false,
          "selected": false,
          "selectable": true,
          "locked": false,
          "grabbable": true,
          "pannable": false,
          "classes": ""
        },
        {
          "data": {
            "id": "wwq7qp3gj6",
            "nodeType": "ANNOTATION",
            "name": "Annotation",
            "connectionId": "921bfae85c38ed45045e07be703d86b8",
            "connectorId": "annotationConnector",
            "capabilityName": "updateAnnotationProperties",
            "type": "action",
            "properties": {
              "backgroundColor": {
                "value": "#f2f3f4ff"
              },
              "annotationTextColor": {
                "value": "#000000"
              },
              "annotation": {
                "value": "Verification Error"
              },
              "width": {
                "value": 240
              },
              "fontSize": {
                "value": 14
              },
              "fontFamily": {
                "value": "sans-serif"
              },
              "cornerRadius": {
                "value": 8
              },
              "strokeEnabled": {
                "value": true
              },
              "strokeWidth": {
                "value": 1
              },
              "strokeColor": {
                "value": "#181818ff"
              }
            },
            "status": "configured",
            "idUnique": "fc7e939oqx"
          },
          "position": {
            "x": 1710,
            "y": 600
          },
          "group": "nodes",
          "removed": false,
          "selected": false,
          "selectable": true,
          "locked": false,
          "grabbable": true,
          "pannable": false,
          "classes": ""
        },
        {
          "data": {
            "id": "eev2hlwvv9",
            "nodeType": "ANNOTATION",
            "name": "Annotation",
            "connectionId": "921bfae85c38ed45045e07be703d86b8",
            "connectorId": "annotationConnector",
            "capabilityName": "updateAnnotationProperties",
            "type": "action",
            "properties": {
              "backgroundColor": {
                "value": "#f2f3f4ff"
              },
              "annotationTextColor": {
                "value": "#000000"
              },
              "annotation": {
                "value": "MFA Enrollment"
              },
              "width": {
                "value": 240
              },
              "fontSize": {
                "value": 14
              },
              "fontFamily": {
                "value": "sans-serif"
              },
              "cornerRadius": {
                "value": 8
              },
              "strokeEnabled": {
                "value": true
              },
              "strokeWidth": {
                "value": 1
              },
              "strokeColor": {
                "value": "#181818ff"
              }
            },
            "status": "configured"
          },
          "position": {
            "x": 1710,
            "y": 360
          },
          "group": "nodes",
          "removed": false,
          "selected": false,
          "selectable": true,
          "locked": false,
          "grabbable": true,
          "pannable": false,
          "classes": ""
        },
        {
          "data": {
            "id": "shuhf5z5i4",
            "nodeType": "ANNOTATION",
            "name": "Annotation",
            "connectionId": "921bfae85c38ed45045e07be703d86b8",
            "connectorId": "annotationConnector",
            "capabilityName": "updateAnnotationProperties",
            "type": "action",
            "properties": {
              "backgroundColor": {
                "value": "#f2f3f4ff"
              },
              "annotationTextColor": {
                "value": "#000000"
              },
              "annotation": {
                "value": "MFA Enrollment Error"
              },
              "width": {
                "value": 240
              },
              "fontSize": {
                "value": 14
              },
              "fontFamily": {
                "value": "sans-serif"
              },
              "cornerRadius": {
                "value": 8
              },
              "strokeEnabled": {
                "value": true
              },
              "strokeWidth": {
                "value": 1
              },
              "strokeColor": {
                "value": "#181818ff"
              }
            },
            "status": "configured",
            "idUnique": "i8wwhn7g9p"
          },
          "position": {
            "x": 2310,
            "y": 600
          },
          "group": "nodes",
          "removed": false,
          "selected": false,
          "selectable": true,
          "locked": false,
          "grabbable": true,
          "pannable": false,
          "classes": ""
        },
        {
          "data": {
            "id": "tgvfzczch3",
            "nodeType": "CONNECTION",
            "connectionId": "867ed4363b2bc21c860085ad2baa817d",
            "connectorId": "httpConnector",
            "name": "Http",
            "label": "Http",
            "status": "configured",
            "capabilityName": "customHTMLTemplate",
            "type": "trigger",
            "properties": {
              "sktemplate": {
                "uiId": "624fbda9a79d412a0e62cc045b410da7",
                "createdDate": 1693913007853,
                "customerId": "f3e47d945ae971a4b4142ec75012d155",
                "description": "",
                "inputSchema": "{\n    \"type\": \"object\",\n    \"properties\": {\n        \"title\": {\n            \"type\": \"string\",\n            \"displayName\": \"Title\",\n            \"preferredControlType\": \"textField\",\n            \"enableParameters\": true,\n            \"propertyName\": \"title\"\n        },\n\t\t\"textOne\": {\n            \"type\": \"string\",\n            \"displayName\": \"Text One\",\n            \"preferredControlType\": \"textField\",\n            \"enableParameters\": true,\n            \"propertyName\": \"textOne\"\n        },\n\t\t\"textTwo\": {\n            \"type\": \"string\",\n            \"displayName\": \"Text Two\",\n            \"preferredControlType\": \"textField\",\n            \"enableParameters\": true,\n            \"propertyName\": \"textTwo\"\n        },\n\t\t\"buttonLabel\": {\n            \"type\": \"string\",\n            \"displayName\": \"Button Label\",\n            \"preferredControlType\": \"textField\",\n            \"enableParameters\": true,\n            \"propertyName\": \"buttonLabel\"\n        }\n    }\n}",
                "name": "Custom Message",
                "outputSchema": null,
                "script": "",
                "style": "",
                "template": "",
                "updatedDate": 1693913396823,
                "validationRules": [],
                "version": "1.0",
                "visibility": "private",
                "companyId": "9343c168-20f8-4262-b335-5250b428bd12",
                "value": "624fbda9a79d412a0e62cc045b410da7"
              },
              "inputSchema": {
                "value": "{\n    \"type\": \"object\",\n    \"properties\": {\n        \"title\": {\n            \"type\": \"string\",\n            \"displayName\": \"Title\",\n            \"preferredControlType\": \"textField\",\n            \"enableParameters\": true,\n            \"propertyName\": \"title\"\n        },\n\t\t\"textOne\": {\n            \"type\": \"string\",\n            \"displayName\": \"Text One\",\n            \"preferredControlType\": \"textField\",\n            \"enableParameters\": true,\n            \"propertyName\": \"textOne\"\n        },\n\t\t\"textTwo\": {\n            \"type\": \"string\",\n            \"displayName\": \"Text Two\",\n            \"preferredControlType\": \"textField\",\n            \"enableParameters\": true,\n            \"propertyName\": \"textTwo\"\n        },\n\t\t\"buttonLabel\": {\n            \"type\": \"string\",\n            \"displayName\": \"Button Label\",\n            \"preferredControlType\": \"textField\",\n            \"enableParameters\": true,\n            \"propertyName\": \"buttonLabel\"\n        }\n    }\n}"
              },
              "outputSchema": {
                "value": null
              },
              "customHTML": {
                "value": "<div\n  class=\"bg-light d-flex flex-column justify-content-center align-items-center position-absolute top-0 start-0 bottom-0 end-0 overflow-auto\">\n  <div style=\"max-width: 400px; min-width: 400px; width: 100%\">\n    <div class=\"card shadow mb-5\">\n      <div class=\"card-body p-5 d-flex flex-column\">\n        <img class=\"companyLogo align-self-center mb-5\" alt=\"{{global.variables.companyName}}\" />\n        \n        {{#if title}}\n        <h1 class=\"text-center mb-4\">{{title}}</h1>\n        {{/if}}\n\n        {{#if textOne}}\n        <p class=\"text-muted text-center\">{{textOne}}</p>\n        {{/if}}\n\n        {{#if textTwo}}\n        <p class=\"text-muted text-center\">{{textTwo}}</p>\n        {{/if}}\n\n        {{#if buttonLabel}}\n        <div class=\"d-flex flex-column\">\n          <button data-id=\"next-button\" type=\"submit\" class=\"btn btn-primary mb-3\" data-skcomponent=\"skbutton\"\n             data-skbuttontype=\"next-event\"  data-skbuttonvalue=\"NEXT\" id=\"btnNext\">\n                {{buttonLabel}}\n            </button>\n        </div>\n        {{/if}}\n        \n      </div>\n    </div>\n  </div>\n</div>"
              },
              "customCSS": {
                "value": ""
              },
              "customScript": {
                "value": ""
              },
              "validationRules": {
                "value": []
              },
              "title": {
                "value": "[\n  {\n    \"children\": [\n      {\n        \"text\": \"Success\"\n      }\n    ]\n  }\n]"
              },
              "textOne": {
                "value": "[\n  {\n    \"children\": [\n      {\n        \"text\": \"Congratulations, you have successfully completed registration.\"\n      }\n    ]\n  }\n]"
              },
              "formFieldsList": {
                "value": [
                  {
                    "preferredControlType": "textField",
                    "preferredDataType": "string",
                    "propertyName": "buttonValue"
                  }
                ]
              },
              "nodeTitle": {
                "value": "Account Successfully Created"
              },
              "nodeDescription": {
                "value": "Render a custom message"
              }
            },
            "idUnique": "16fkjw5hoo"
          },
          "position": {
            "x": 2430,
            "y": 480
          },
          "group": "nodes",
          "removed": false,
          "selected": false,
          "selectable": true,
          "locked": false,
          "grabbable": true,
          "pannable": false,
          "classes": ""
        },
        {
          "data": {
            "id": "j08ogske6m",
            "nodeType": "ANNOTATION",
            "name": "Annotation",
            "connectionId": "921bfae85c38ed45045e07be703d86b8",
            "connectorId": "annotationConnector",
            "capabilityName": "updateAnnotationProperties",
            "type": "action",
            "properties": {
              "backgroundColor": {
                "value": "#f2f3f4ff"
              },
              "annotationTextColor": {
                "value": "#000000"
              },
              "annotation": {
                "value": "Account Success"
              },
              "width": {
                "value": 240
              },
              "fontSize": {
                "value": 14
              },
              "fontFamily": {
                "value": "sans-serif"
              },
              "cornerRadius": {
                "value": 8
              },
              "strokeEnabled": {
                "value": true
              },
              "strokeWidth": {
                "value": 1
              },
              "strokeColor": {
                "value": "#181818ff"
              }
            },
            "status": "configured",
            "idUnique": "9w1ru50mr3"
          },
          "position": {
            "x": 2310,
            "y": 360
          },
          "group": "nodes",
          "removed": false,
          "selected": false,
          "selectable": true,
          "locked": false,
          "grabbable": true,
          "pannable": false,
          "classes": ""
        }
      ],
      "edges": [
        {
          "data": {
            "id": "v52dpqh660",
            "source": "omghnpt8gt",
            "target": "64lc0zonuu"
          },
          "position": {
            "x": 0,
            "y": 0
          },
          "group": "edges",
          "removed": false,
          "selected": false,
          "selectable": true,
          "locked": false,
          "grabbable": true,
          "pannable": true,
          "classes": ""
        },
        {
          "data": {
            "id": "ys95cc6ygz",
            "source": "3p9s1p9kfx",
            "target": "bzmvingg2c"
          },
          "position": {
            "x": 0,
            "y": 0
          },
          "group": "edges",
          "removed": false,
          "selected": false,
          "selectable": true,
          "locked": false,
          "grabbable": true,
          "pannable": true,
          "classes": ""
        },
        {
          "data": {
            "id": "uhyxs442p5",
            "source": "9g1rb2rxt5",
            "target": "kotjm31vdk"
          },
          "position": {
            "x": 0,
            "y": 0
          },
          "group": "edges",
          "removed": false,
          "selected": false,
          "selectable": true,
          "locked": false,
          "grabbable": true,
          "pannable": true,
          "classes": ""
        },
        {
          "data": {
            "id": "eocacuudv8",
            "source": "64lc0zonuu",
            "target": "rogr26k0ca"
          },
          "position": {
            "x": 0,
            "y": 0
          },
          "group": "edges",
          "removed": false,
          "selected": false,
          "selectable": true,
          "locked": false,
          "grabbable": true,
          "pannable": true,
          "classes": ""
        },
        {
          "data": {
            "id": "5ksq92iyxm",
            "source": "591k4nizoj",
            "target": "bubzo4dlxp"
          },
          "position": {
            "x": 0,
            "y": 0
          },
          "group": "edges",
          "removed": false,
          "selected": false,
          "selectable": true,
          "locked": false,
          "grabbable": true,
          "pannable": true,
          "classes": ""
        },
        {
          "data": {
            "id": "euzq6albur",
            "source": "bubzo4dlxp",
            "target": "b03wrisvgh"
          },
          "position": {
            "x": 0,
            "y": 0
          },
          "group": "edges",
          "removed": false,
          "selected": false,
          "selectable": true,
          "locked": false,
          "grabbable": true,
          "pannable": true,
          "classes": ""
        },
        {
          "data": {
            "id": "9sss3dcmss",
            "source": "rogr26k0ca",
            "target": "9g1rb2rxt5"
          },
          "position": {
            "x": 0,
            "y": 0
          },
          "group": "edges",
          "removed": false,
          "selected": false,
          "selectable": true,
          "locked": false,
          "grabbable": true,
          "pannable": true,
          "classes": ""
        },
        {
          "data": {
            "id": "7hqisor26c",
            "source": "oyrj36mdip",
            "target": "q3tujxeb1w"
          },
          "position": {
            "x": 0,
            "y": 0
          },
          "group": "edges",
          "removed": false,
          "selected": false,
          "selectable": true,
          "locked": false,
          "grabbable": true,
          "pannable": true,
          "classes": ""
        },
        {
          "data": {
            "id": "djs8rdnju9",
            "source": "l68q24zfrg",
            "target": "omghnpt8gt"
          },
          "position": {
            "x": 0,
            "y": 0
          },
          "group": "edges",
          "removed": false,
          "selected": false,
          "selectable": true,
          "locked": false,
          "grabbable": true,
          "pannable": true,
          "classes": ""
        },
        {
          "data": {
            "id": "ashui9gyjw",
            "source": "bzmvingg2c",
            "target": "oyrj36mdip"
          },
          "position": {
            "x": 0,
            "y": 0
          },
          "group": "edges",
          "removed": false,
          "selected": false,
          "selectable": true,
          "locked": false,
          "grabbable": true,
          "pannable": true,
          "classes": ""
        },
        {
          "data": {
            "id": "h8h5z6rvpi",
            "source": "591k4nizoj",
            "target": "70xyz374za"
          },
          "position": {
            "x": 0,
            "y": 0
          },
          "group": "edges",
          "removed": false,
          "selected": false,
          "selectable": true,
          "locked": false,
          "grabbable": true,
          "pannable": true,
          "classes": ""
        },
        {
          "data": {
            "id": "9mhrhnkq9m",
            "source": "q3tujxeb1w",
            "target": "hwm8kns5vd"
          },
          "position": {
            "x": 0,
            "y": 0
          },
          "group": "edges",
          "removed": false,
          "selected": false,
          "selectable": true,
          "locked": false,
          "grabbable": true,
          "pannable": true,
          "classes": ""
        },
        {
          "data": {
            "id": "a71nz4dxcz",
            "source": "rcbpcr6g10",
            "target": "l68q24zfrg"
          },
          "position": {
            "x": 0,
            "y": 0
          },
          "group": "edges",
          "removed": false,
          "selected": false,
          "selectable": true,
          "locked": false,
          "grabbable": true,
          "pannable": true,
          "classes": ""
        },
        {
          "data": {
            "id": "ms8i4ffyqk",
            "source": "hwm8kns5vd",
            "target": "591k4nizoj"
          },
          "position": {
            "x": 0,
            "y": 0
          },
          "group": "edges",
          "removed": false,
          "selected": false,
          "selectable": true,
          "locked": false,
          "grabbable": true,
          "pannable": true,
          "classes": ""
        },
        {
          "data": {
            "id": "iuw0q5p8eh",
            "source": "b03wrisvgh",
            "target": "rcbpcr6g10"
          },
          "position": {
            "x": 0,
            "y": 0
          },
          "group": "edges",
          "removed": false,
          "selected": false,
          "selectable": true,
          "locked": false,
          "grabbable": true,
          "pannable": true,
          "classes": ""
        },
        {
          "data": {
            "id": "lporlaz6lu",
            "source": "l68q24zfrg",
            "target": "z2mcqw4azg"
          },
          "position": {
            "x": 0,
            "y": 0
          },
          "group": "edges",
          "removed": false,
          "selected": false,
          "selectable": true,
          "locked": false,
          "grabbable": true,
          "pannable": true,
          "classes": ""
        },
        {
          "data": {
            "id": "7jso3e9be6",
            "source": "64lc0zonuu",
            "target": "kotjm31vdk"
          },
          "position": {
            "x": 0,
            "y": 0
          },
          "group": "edges",
          "removed": false,
          "selected": false,
          "selectable": true,
          "locked": false,
          "grabbable": true,
          "pannable": true,
          "classes": ""
        },
        {
          "data": {
            "id": "ftfrvcrca9",
            "source": "9g1rb2rxt5",
            "target": "tgvfzczch3"
          },
          "position": {
            "x": 0,
            "y": 0
          },
          "group": "edges",
          "removed": false,
          "selected": false,
          "selectable": true,
          "locked": false,
          "grabbable": true,
          "pannable": true,
          "classes": ""
        }
      ]
    },
    "data": {},
    "zoomingEnabled": true,
    "userZoomingEnabled": true,
    "zoom": 1,
    "minZoom": 1e-50,
    "maxZoom": 1e+50,
    "panningEnabled": true,
    "userPanningEnabled": true,
    "pan": {
      "x": 0,
      "y": 0
    },
    "boxSelectionEnabled": true,
    "renderer": {
      "name": "null"
    }
  },
  "flowColor": "#E3F0FF",
  "savedDate": 1698064942852,
  "variables": [
    {
      "context": "flowInstance",
      "createdDate": 1695902607447,
      "fields": {
        "type": "string",
        "displayName": "",
        "min": 0,
        "max": 2000
      },
      "type": "property",
      "visibility": "private",
      "name": "companyName##SK##flowInstance",
      "companyId": "16395f68-5373-4a81-bf1e-6c61f6cacdd7"
    },
    {
      "context": "flowInstance",
      "createdDate": 1695902607456,
      "fields": {
        "type": "string",
        "displayName": "",
        "mutable": true,
        "min": 0,
        "max": 2000
      },
      "type": "property",
      "visibility": "private",
      "name": "populationId##SK##flowInstance",
      "companyId": "16395f68-5373-4a81-bf1e-6c61f6cacdd7"
    }
  ],
  "connections": []
}